superutilities/__init__.py
superutilities/main.py
superutilities-0.2.4.dist-info/licenses/LICENSE
superutilities-0.2.4.dist-info/METADATA
superutilities-0.2.4.dist-info/WHEEL
superutilities-0.2.4.dist-info/top_level.txt
superutilities-0.2.4.dist-info/RECORD
