Metadata-Version: 2.4
Name: superutilities
Version: 0.2.4
Summary: A custom made python 3 file that adds some features that aim to streamline the coding process. This was made primarily for a python coding class, apologies it is a little out of the blue.
Author-email: EnvyingGolem47 <envyinggolem47@projectnightfall.net>
License-Expression: MIT
Project-URL: Homepage, https://github.com/EnvyingGolem47/SuperUtilities-Python3
Keywords: superutilities,super,utilities
Classifier: Programming Language :: Python
Classifier: Programming Language :: Python :: 3
Requires-Python: >=3.9
License-File: LICENSE
Requires-Dist: flask>=3.0.0
Dynamic: license-file
